shared_camera/__init__.py
shared_camera/no_feed.jpg
shared_camera-0.1.dist-info/LICENSE.md
shared_camera-0.1.dist-info/METADATA
shared_camera-0.1.dist-info/WHEEL
shared_camera-0.1.dist-info/top_level.txt
shared_camera-0.1.dist-info/RECORD
