Metadata-Version: 2.1
Name: shared-camera
Version: 0.1
Summary: inter process camera interface
Home-page: https://github.com/NeonGeckoCom/shared_camera
Author: Neongecko
Author-email: developers@neon.ai
License: BSD-3
License-File: LICENSE.md
